virgo/__init__.py
virgo/ftf.grc
virgo/map.txt
virgo/run_ftf.py
virgo/run_wola.py
virgo/virgo.py
virgo/wola.grc
astro_virgo-3.8.2.dist-info/LICENSE
astro_virgo-3.8.2.dist-info/METADATA
astro_virgo-3.8.2.dist-info/WHEEL
astro_virgo-3.8.2.dist-info/entry_points.txt
astro_virgo-3.8.2.dist-info/top_level.txt
astro_virgo-3.8.2.dist-info/RECORD
