Metadata-Version: 2.1
Name: astro-virgo
Version: 3.8.2
Summary: A Versatile Spectrometer for Radio Astronomy
Home-page: https://github.com/0xCoto/Virgo
Author: Apostolos Spanakis-Misirlis
Author-email: 0xcoto@protonmail.com
Classifier: Programming Language :: Python
Classifier: License :: OSI Approved :: GNU General Public License v3 (GPLv3)
Classifier: Operating System :: OS Independent
Requires-Python: >=2.7
License-File: LICENSE
Requires-Dist: numpy
Requires-Dist: matplotlib
Requires-Dist: astropy
